{
    "name": "vagrant_tombstone_wall",
    "bullets": [
        {
            "originPos": {
                "x": 2.0,
                "y": 19.0
            },
            "originVlc": {
                "x": 0,
                "y": 0
            },
            "speed": 3.0,
            "gravity": {
                "x": 0.0,
                "y": -1.5707963
            },
            "initialAngle": 0,
            "angleSpeed": 0.0,
            "useVelocityAngle": false,
            "polarForm": {
                "x": 1,
                "y": -1.5707963267948966
            },
            "radiusVlc": 0,
            "radiusAccel": 0,
            "thetaVlc": 0,
            "thetaAccel": 0,
            "polynomial": {
                "x": 0,
                "y": 0,
                "z": 0,
                "w": 0
            },
            "typeName": "tombstone",
            "scale": {
                "x": 1.6,
                "y": 1.6
            },
            "color": {
                "x": 0,
                "y": 0,
                "z": 0,
                "w": 0
            },
            "appearTime": 0.0,
            "appearDuration": 0.05,
            "life": 7.5,
            "random": 0,
            "unCounterable": true
        },
        {
            "originPos": {
                "x": 14.0,
                "y": 19.0
            },
            "originVlc": {
                "x": 0,
                "y": 0
            },
            "speed": 3.0,
            "gravity": {
                "x": 0.0,
                "y": -1.5707963
            },
            "initialAngle": 0,
            "angleSpeed": 0.0,
            "useVelocityAngle": false,
            "polarForm": {
                "x": 1,
                "y": -1.5707963267948966
            },
            "radiusVlc": 0,
            "radiusAccel": 0,
            "thetaVlc": 0,
            "thetaAccel": 0,
            "polynomial": {
                "x": 0,
                "y": 0,
                "z": 0,
                "w": 0
            },
            "typeName": "tombstone",
            "scale": {
                "x": 1.6,
                "y": 1.6
            },
            "color": {
                "x": 0,
                "y": 0,
                "z": 0,
                "w": 0
            },
            "appearTime": 0.0,
            "appearDuration": 0.05,
            "life": 7.5,
            "random": 0,
            "unCounterable": true
        },
        {
            "originPos": {
                "x": 18.0,
                "y": 19.0
            },
            "originVlc": {
                "x": 0,
                "y": 0
            },
            "speed": 3.0,
            "gravity": {
                "x": 0.0,
                "y": -1.5707963
            },
            "initialAngle": 0,
            "angleSpeed": 0.0,
            "useVelocityAngle": false,
            "polarForm": {
                "x": 1,
                "y": -1.5707963267948966
            },
            "radiusVlc": 0,
            "radiusAccel": 0,
            "thetaVlc": 0,
            "thetaAccel": 0,
            "polynomial": {
                "x": 0,
                "y": 0,
                "z": 0,
                "w": 0
            },
            "typeName": "tombstone",
            "scale": {
                "x": 1.6,
                "y": 1.6
            },
            "color": {
                "x": 0,
                "y": 0,
                "z": 0,
                "w": 0
            },
            "appearTime": 0.0,
            "appearDuration": 0.05,
            "life": 7.5,
            "random": 0,
            "unCounterable": true
        },
        {
            "originPos": {
                "x": 22.0,
                "y": 19.0
            },
            "originVlc": {
                "x": 0,
                "y": 0
            },
            "speed": 3.0,
            "gravity": {
                "x": 0.0,
                "y": -1.5707963
            },
            "initialAngle": 0,
            "angleSpeed": 0.0,
            "useVelocityAngle": false,
            "polarForm": {
                "x": 1,
                "y": -1.5707963267948966
            },
            "radiusVlc": 0,
            "radiusAccel": 0,
            "thetaVlc": 0,
            "thetaAccel": 0,
            "polynomial": {
                "x": 0,
                "y": 0,
                "z": 0,
                "w": 0
            },
            "typeName": "tombstone",
            "scale": {
                "x": 1.6,
                "y": 1.6
            },
            "color": {
                "x": 0,
                "y": 0,
                "z": 0,
                "w": 0
            },
            "appearTime": 0.0,
            "appearDuration": 0.05,
            "life": 7.5,
            "random": 0,
            "unCounterable": true
        },
        {
            "originPos": {
                "x": 26.0,
                "y": 19.0
            },
            "originVlc": {
                "x": 0,
                "y": 0
            },
            "speed": 3.0,
            "gravity": {
                "x": 0.0,
                "y": -1.5707963
            },
            "initialAngle": 0,
            "angleSpeed": 0.0,
            "useVelocityAngle": false,
            "polarForm": {
                "x": 1,
                "y": -1.5707963267948966
            },
            "radiusVlc": 0,
            "radiusAccel": 0,
            "thetaVlc": 0,
            "thetaAccel": 0,
            "polynomial": {
                "x": 0,
                "y": 0,
                "z": 0,
                "w": 0
            },
            "typeName": "tombstone",
            "scale": {
                "x": 1.6,
                "y": 1.6
            },
            "color": {
                "x": 0,
                "y": 0,
                "z": 0,
                "w": 0
            },
            "appearTime": 0.0,
            "appearDuration": 0.05,
            "life": 7.5,
            "random": 0,
            "unCounterable": true
        },
        {
            "originPos": {
                "x": 30.0,
                "y": 19.0
            },
            "originVlc": {
                "x": 0,
                "y": 0
            },
            "speed": 3.0,
            "gravity": {
                "x": 0.0,
                "y": -1.5707963
            },
            "initialAngle": 0,
            "angleSpeed": 0.0,
            "useVelocityAngle": false,
            "polarForm": {
                "x": 1,
                "y": -1.5707963267948966
            },
            "radiusVlc": 0,
            "radiusAccel": 0,
            "thetaVlc": 0,
            "thetaAccel": 0,
            "polynomial": {
                "x": 0,
                "y": 0,
                "z": 0,
                "w": 0
            },
            "typeName": "tombstone",
            "scale": {
                "x": 1.6,
                "y": 1.6
            },
            "color": {
                "x": 0,
                "y": 0,
                "z": 0,
                "w": 0
            },
            "appearTime": 0.0,
            "appearDuration": 0.05,
            "life": 7.5,
            "random": 0,
            "unCounterable": true
        },
        {
            "originPos": {
                "x": 2.0,
                "y": 19.0
            },
            "originVlc": {
                "x": 0,
                "y": 0
            },
            "speed": 3.0,
            "gravity": {
                "x": 0.0,
                "y": -1.5707963
            },
            "initialAngle": 0,
            "angleSpeed": 0.0,
            "useVelocityAngle": false,
            "polarForm": {
                "x": 1,
                "y": -1.5707963267948966
            },
            "radiusVlc": 0,
            "radiusAccel": 0,
            "thetaVlc": 0,
            "thetaAccel": 0,
            "polynomial": {
                "x": 0,
                "y": 0,
                "z": 0,
                "w": 0
            },
            "typeName": "tombstone",
            "scale": {
                "x": 1.6,
                "y": 1.6
            },
            "color": {
                "x": 0,
                "y": 0,
                "z": 0,
                "w": 0
            },
            "appearTime": 3.8,
            "appearDuration": 0.05,
            "life": 11.3,
            "random": 0,
            "unCounterable": true
        },
        {
            "originPos": {
                "x": 6.0,
                "y": 19.0
            },
            "originVlc": {
                "x": 0,
                "y": 0
            },
            "speed": 3.0,
            "gravity": {
                "x": 0.0,
                "y": -1.5707963
            },
            "initialAngle": 0,
            "angleSpeed": 0.0,
            "useVelocityAngle": false,
            "polarForm": {
                "x": 1,
                "y": -1.5707963267948966
            },
            "radiusVlc": 0,
            "radiusAccel": 0,
            "thetaVlc": 0,
            "thetaAccel": 0,
            "polynomial": {
                "x": 0,
                "y": 0,
                "z": 0,
                "w": 0
            },
            "typeName": "tombstone",
            "scale": {
                "x": 1.6,
                "y": 1.6
            },
            "color": {
                "x": 0,
                "y": 0,
                "z": 0,
                "w": 0
            },
            "appearTime": 3.8,
            "appearDuration": 0.05,
            "life": 11.3,
            "random": 0,
            "unCounterable": true
        },
        {
            "originPos": {
                "x": 10.0,
                "y": 19.0
            },
            "originVlc": {
                "x": 0,
                "y": 0
            },
            "speed": 3.0,
            "gravity": {
                "x": 0.0,
                "y": -1.5707963
            },
            "initialAngle": 0,
            "angleSpeed": 0.0,
            "useVelocityAngle": false,
            "polarForm": {
                "x": 1,
                "y": -1.5707963267948966
            },
            "radiusVlc": 0,
            "radiusAccel": 0,
            "thetaVlc": 0,
            "thetaAccel": 0,
            "polynomial": {
                "x": 0,
                "y": 0,
                "z": 0,
                "w": 0
            },
            "typeName": "tombstone",
            "scale": {
                "x": 1.6,
                "y": 1.6
            },
            "color": {
                "x": 0,
                "y": 0,
                "z": 0,
                "w": 0
            },
            "appearTime": 3.8,
            "appearDuration": 0.05,
            "life": 11.3,
            "random": 0,
            "unCounterable": true
        },
        {
            "originPos": {
                "x": 22.0,
                "y": 19.0
            },
            "originVlc": {
                "x": 0,
                "y": 0
            },
            "speed": 3.0,
            "gravity": {
                "x": 0.0,
                "y": -1.5707963
            },
            "initialAngle": 0,
            "angleSpeed": 0.0,
            "useVelocityAngle": false,
            "polarForm": {
                "x": 1,
                "y": -1.5707963267948966
            },
            "radiusVlc": 0,
            "radiusAccel": 0,
            "thetaVlc": 0,
            "thetaAccel": 0,
            "polynomial": {
                "x": 0,
                "y": 0,
                "z": 0,
                "w": 0
            },
            "typeName": "tombstone",
            "scale": {
                "x": 1.6,
                "y": 1.6
            },
            "color": {
                "x": 0,
                "y": 0,
                "z": 0,
                "w": 0
            },
            "appearTime": 3.8,
            "appearDuration": 0.05,
            "life": 11.3,
            "random": 0,
            "unCounterable": true
        },
        {
            "originPos": {
                "x": 26.0,
                "y": 19.0
            },
            "originVlc": {
                "x": 0,
                "y": 0
            },
            "speed": 3.0,
            "gravity": {
                "x": 0.0,
                "y": -1.5707963
            },
            "initialAngle": 0,
            "angleSpeed": 0.0,
            "useVelocityAngle": false,
            "polarForm": {
                "x": 1,
                "y": -1.5707963267948966
            },
            "radiusVlc": 0,
            "radiusAccel": 0,
            "thetaVlc": 0,
            "thetaAccel": 0,
            "polynomial": {
                "x": 0,
                "y": 0,
                "z": 0,
                "w": 0
            },
            "typeName": "tombstone",
            "scale": {
                "x": 1.6,
                "y": 1.6
            },
            "color": {
                "x": 0,
                "y": 0,
                "z": 0,
                "w": 0
            },
            "appearTime": 3.8,
            "appearDuration": 0.05,
            "life": 11.3,
            "random": 0,
            "unCounterable": true
        },
        {
            "originPos": {
                "x": 30.0,
                "y": 19.0
            },
            "originVlc": {
                "x": 0,
                "y": 0
            },
            "speed": 3.0,
            "gravity": {
                "x": 0.0,
                "y": -1.5707963
            },
            "initialAngle": 0,
            "angleSpeed": 0.0,
            "useVelocityAngle": false,
            "polarForm": {
                "x": 1,
                "y": -1.5707963267948966
            },
            "radiusVlc": 0,
            "radiusAccel": 0,
            "thetaVlc": 0,
            "thetaAccel": 0,
            "polynomial": {
                "x": 0,
                "y": 0,
                "z": 0,
                "w": 0
            },
            "typeName": "tombstone",
            "scale": {
                "x": 1.6,
                "y": 1.6
            },
            "color": {
                "x": 0,
                "y": 0,
                "z": 0,
                "w": 0
            },
            "appearTime": 3.8,
            "appearDuration": 0.05,
            "life": 11.3,
            "random": 0,
            "unCounterable": true
        },
        {
            "originPos": {
                "x": 2.0,
                "y": 19.0
            },
            "originVlc": {
                "x": 0,
                "y": 0
            },
            "speed": 3.0,
            "gravity": {
                "x": 0.0,
                "y": -1.5707963
            },
            "initialAngle": 0,
            "angleSpeed": 0.0,
            "useVelocityAngle": false,
            "polarForm": {
                "x": 1,
                "y": -1.5707963267948966
            },
            "radiusVlc": 0,
            "radiusAccel": 0,
            "thetaVlc": 0,
            "thetaAccel": 0,
            "polynomial": {
                "x": 0,
                "y": 0,
                "z": 0,
                "w": 0
            },
            "typeName": "tombstone",
            "scale": {
                "x": 1.6,
                "y": 1.6
            },
            "color": {
                "x": 0,
                "y": 0,
                "z": 0,
                "w": 0
            },
            "appearTime": 7.6,
            "appearDuration": 0.05,
            "life": 15.1,
            "random": 0,
            "unCounterable": true
        },
        {
            "originPos": {
                "x": 6.0,
                "y": 19.0
            },
            "originVlc": {
                "x": 0,
                "y": 0
            },
            "speed": 3.0,
            "gravity": {
                "x": 0.0,
                "y": -1.5707963
            },
            "initialAngle": 0,
            "angleSpeed": 0.0,
            "useVelocityAngle": false,
            "polarForm": {
                "x": 1,
                "y": -1.5707963267948966
            },
            "radiusVlc": 0,
            "radiusAccel": 0,
            "thetaVlc": 0,
            "thetaAccel": 0,
            "polynomial": {
                "x": 0,
                "y": 0,
                "z": 0,
                "w": 0
            },
            "typeName": "tombstone",
            "scale": {
                "x": 1.6,
                "y": 1.6
            },
            "color": {
                "x": 0,
                "y": 0,
                "z": 0,
                "w": 0
            },
            "appearTime": 7.6,
            "appearDuration": 0.05,
            "life": 15.1,
            "random": 0,
            "unCounterable": true
        },
        {
            "originPos": {
                "x": 10.0,
                "y": 19.0
            },
            "originVlc": {
                "x": 0,
                "y": 0
            },
            "speed": 3.0,
            "gravity": {
                "x": 0.0,
                "y": -1.5707963
            },
            "initialAngle": 0,
            "angleSpeed": 0.0,
            "useVelocityAngle": false,
            "polarForm": {
                "x": 1,
                "y": -1.5707963267948966
            },
            "radiusVlc": 0,
            "radiusAccel": 0,
            "thetaVlc": 0,
            "thetaAccel": 0,
            "polynomial": {
                "x": 0,
                "y": 0,
                "z": 0,
                "w": 0
            },
            "typeName": "tombstone",
            "scale": {
                "x": 1.6,
                "y": 1.6
            },
            "color": {
                "x": 0,
                "y": 0,
                "z": 0,
                "w": 0
            },
            "appearTime": 7.6,
            "appearDuration": 0.05,
            "life": 15.1,
            "random": 0,
            "unCounterable": true
        },
        {
            "originPos": {
                "x": 14.0,
                "y": 19.0
            },
            "originVlc": {
                "x": 0,
                "y": 0
            },
            "speed": 3.0,
            "gravity": {
                "x": 0.0,
                "y": -1.5707963
            },
            "initialAngle": 0,
            "angleSpeed": 0.0,
            "useVelocityAngle": false,
            "polarForm": {
                "x": 1,
                "y": -1.5707963267948966
            },
            "radiusVlc": 0,
            "radiusAccel": 0,
            "thetaVlc": 0,
            "thetaAccel": 0,
            "polynomial": {
                "x": 0,
                "y": 0,
                "z": 0,
                "w": 0
            },
            "typeName": "tombstone",
            "scale": {
                "x": 1.6,
                "y": 1.6
            },
            "color": {
                "x": 0,
                "y": 0,
                "z": 0,
                "w": 0
            },
            "appearTime": 7.6,
            "appearDuration": 0.05,
            "life": 15.1,
            "random": 0,
            "unCounterable": true
        },
        {
            "originPos": {
                "x": 26.0,
                "y": 19.0
            },
            "originVlc": {
                "x": 0,
                "y": 0
            },
            "speed": 3.0,
            "gravity": {
                "x": 0.0,
                "y": -1.5707963
            },
            "initialAngle": 0,
            "angleSpeed": 0.0,
            "useVelocityAngle": false,
            "polarForm": {
                "x": 1,
                "y": -1.5707963267948966
            },
            "radiusVlc": 0,
            "radiusAccel": 0,
            "thetaVlc": 0,
            "thetaAccel": 0,
            "polynomial": {
                "x": 0,
                "y": 0,
                "z": 0,
                "w": 0
            },
            "typeName": "tombstone",
            "scale": {
                "x": 1.6,
                "y": 1.6
            },
            "color": {
                "x": 0,
                "y": 0,
                "z": 0,
                "w": 0
            },
            "appearTime": 7.6,
            "appearDuration": 0.05,
            "life": 15.1,
            "random": 0,
            "unCounterable": true
        },
        {
            "originPos": {
                "x": 30.0,
                "y": 19.0
            },
            "originVlc": {
                "x": 0,
                "y": 0
            },
            "speed": 3.0,
            "gravity": {
                "x": 0.0,
                "y": -1.5707963
            },
            "initialAngle": 0,
            "angleSpeed": 0.0,
            "useVelocityAngle": false,
            "polarForm": {
                "x": 1,
                "y": -1.5707963267948966
            },
            "radiusVlc": 0,
            "radiusAccel": 0,
            "thetaVlc": 0,
            "thetaAccel": 0,
            "polynomial": {
                "x": 0,
                "y": 0,
                "z": 0,
                "w": 0
            },
            "typeName": "tombstone",
            "scale": {
                "x": 1.6,
                "y": 1.6
            },
            "color": {
                "x": 0,
                "y": 0,
                "z": 0,
                "w": 0
            },
            "appearTime": 7.6,
            "appearDuration": 0.05,
            "life": 15.1,
            "random": 0,
            "unCounterable": true
        },
        {
            "originPos": {
                "x": 2.0,
                "y": 19.0
            },
            "originVlc": {
                "x": 0,
                "y": 0
            },
            "speed": 3.0,
            "gravity": {
                "x": 0.0,
                "y": -1.5707963
            },
            "initialAngle": 0,
            "angleSpeed": 0.0,
            "useVelocityAngle": false,
            "polarForm": {
                "x": 1,
                "y": -1.5707963267948966
            },
            "radiusVlc": 0,
            "radiusAccel": 0,
            "thetaVlc": 0,
            "thetaAccel": 0,
            "polynomial": {
                "x": 0,
                "y": 0,
                "z": 0,
                "w": 0
            },
            "typeName": "tombstone",
            "scale": {
                "x": 1.6,
                "y": 1.6
            },
            "color": {
                "x": 0,
                "y": 0,
                "z": 0,
                "w": 0
            },
            "appearTime": 11.4,
            "appearDuration": 0.05,
            "life": 18.9,
            "random": 0,
            "unCounterable": true
        },
        {
            "originPos": {
                "x": 6.0,
                "y": 19.0
            },
            "originVlc": {
                "x": 0,
                "y": 0
            },
            "speed": 3.0,
            "gravity": {
                "x": 0.0,
                "y": -1.5707963
            },
            "initialAngle": 0,
            "angleSpeed": 0.0,
            "useVelocityAngle": false,
            "polarForm": {
                "x": 1,
                "y": -1.5707963267948966
            },
            "radiusVlc": 0,
            "radiusAccel": 0,
            "thetaVlc": 0,
            "thetaAccel": 0,
            "polynomial": {
                "x": 0,
                "y": 0,
                "z": 0,
                "w": 0
            },
            "typeName": "tombstone",
            "scale": {
                "x": 1.6,
                "y": 1.6
            },
            "color": {
                "x": 0,
                "y": 0,
                "z": 0,
                "w": 0
            },
            "appearTime": 11.4,
            "appearDuration": 0.05,
            "life": 18.9,
            "random": 0,
            "unCounterable": true
        },
        {
            "originPos": {
                "x": 10.0,
                "y": 19.0
            },
            "originVlc": {
                "x": 0,
                "y": 0
            },
            "speed": 3.0,
            "gravity": {
                "x": 0.0,
                "y": -1.5707963
            },
            "initialAngle": 0,
            "angleSpeed": 0.0,
            "useVelocityAngle": false,
            "polarForm": {
                "x": 1,
                "y": -1.5707963267948966
            },
            "radiusVlc": 0,
            "radiusAccel": 0,
            "thetaVlc": 0,
            "thetaAccel": 0,
            "polynomial": {
                "x": 0,
                "y": 0,
                "z": 0,
                "w": 0
            },
            "typeName": "tombstone",
            "scale": {
                "x": 1.6,
                "y": 1.6
            },
            "color": {
                "x": 0,
                "y": 0,
                "z": 0,
                "w": 0
            },
            "appearTime": 11.4,
            "appearDuration": 0.05,
            "life": 18.9,
            "random": 0,
            "unCounterable": true
        },
        {
            "originPos": {
                "x": 14.0,
                "y": 19.0
            },
            "originVlc": {
                "x": 0,
                "y": 0
            },
            "speed": 3.0,
            "gravity": {
                "x": 0.0,
                "y": -1.5707963
            },
            "initialAngle": 0,
            "angleSpeed": 0.0,
            "useVelocityAngle": false,
            "polarForm": {
                "x": 1,
                "y": -1.5707963267948966
            },
            "radiusVlc": 0,
            "radiusAccel": 0,
            "thetaVlc": 0,
            "thetaAccel": 0,
            "polynomial": {
                "x": 0,
                "y": 0,
                "z": 0,
                "w": 0
            },
            "typeName": "tombstone",
            "scale": {
                "x": 1.6,
                "y": 1.6
            },
            "color": {
                "x": 0,
                "y": 0,
                "z": 0,
                "w": 0
            },
            "appearTime": 11.4,
            "appearDuration": 0.05,
            "life": 18.9,
            "random": 0,
            "unCounterable": true
        },
        {
            "originPos": {
                "x": 18.0,
                "y": 19.0
            },
            "originVlc": {
                "x": 0,
                "y": 0
            },
            "speed": 3.0,
            "gravity": {
                "x": 0.0,
                "y": -1.5707963
            },
            "initialAngle": 0,
            "angleSpeed": 0.0,
            "useVelocityAngle": false,
            "polarForm": {
                "x": 1,
                "y": -1.5707963267948966
            },
            "radiusVlc": 0,
            "radiusAccel": 0,
            "thetaVlc": 0,
            "thetaAccel": 0,
            "polynomial": {
                "x": 0,
                "y": 0,
                "z": 0,
                "w": 0
            },
            "typeName": "tombstone",
            "scale": {
                "x": 1.6,
                "y": 1.6
            },
            "color": {
                "x": 0,
                "y": 0,
                "z": 0,
                "w": 0
            },
            "appearTime": 11.4,
            "appearDuration": 0.05,
            "life": 18.9,
            "random": 0,
            "unCounterable": true
        },
        {
            "originPos": {
                "x": 30.0,
                "y": 19.0
            },
            "originVlc": {
                "x": 0,
                "y": 0
            },
            "speed": 3.0,
            "gravity": {
                "x": 0.0,
                "y": -1.5707963
            },
            "initialAngle": 0,
            "angleSpeed": 0.0,
            "useVelocityAngle": false,
            "polarForm": {
                "x": 1,
                "y": -1.5707963267948966
            },
            "radiusVlc": 0,
            "radiusAccel": 0,
            "thetaVlc": 0,
            "thetaAccel": 0,
            "polynomial": {
                "x": 0,
                "y": 0,
                "z": 0,
                "w": 0
            },
            "typeName": "tombstone",
            "scale": {
                "x": 1.6,
                "y": 1.6
            },
            "color": {
                "x": 0,
                "y": 0,
                "z": 0,
                "w": 0
            },
            "appearTime": 11.4,
            "appearDuration": 0.05,
            "life": 18.9,
            "random": 0,
            "unCounterable": true
        },
        {
            "originPos": {
                "x": 2.0,
                "y": 19.0
            },
            "originVlc": {
                "x": 0,
                "y": 0
            },
            "speed": 3.0,
            "gravity": {
                "x": 0.0,
                "y": -1.5707963
            },
            "initialAngle": 0,
            "angleSpeed": 0.0,
            "useVelocityAngle": false,
            "polarForm": {
                "x": 1,
                "y": -1.5707963267948966
            },
            "radiusVlc": 0,
            "radiusAccel": 0,
            "thetaVlc": 0,
            "thetaAccel": 0,
            "polynomial": {
                "x": 0,
                "y": 0,
                "z": 0,
                "w": 0
            },
            "typeName": "tombstone",
            "scale": {
                "x": 1.6,
                "y": 1.6
            },
            "color": {
                "x": 0,
                "y": 0,
                "z": 0,
                "w": 0
            },
            "appearTime": 15.2,
            "appearDuration": 0.05,
            "life": 22.7,
            "random": 0,
            "unCounterable": true
        },
        {
            "originPos": {
                "x": 6.0,
                "y": 19.0
            },
            "originVlc": {
                "x": 0,
                "y": 0
            },
            "speed": 3.0,
            "gravity": {
                "x": 0.0,
                "y": -1.5707963
            },
            "initialAngle": 0,
            "angleSpeed": 0.0,
            "useVelocityAngle": false,
            "polarForm": {
                "x": 1,
                "y": -1.5707963267948966
            },
            "radiusVlc": 0,
            "radiusAccel": 0,
            "thetaVlc": 0,
            "thetaAccel": 0,
            "polynomial": {
                "x": 0,
                "y": 0,
                "z": 0,
                "w": 0
            },
            "typeName": "tombstone",
            "scale": {
                "x": 1.6,
                "y": 1.6
            },
            "color": {
                "x": 0,
                "y": 0,
                "z": 0,
                "w": 0
            },
            "appearTime": 15.2,
            "appearDuration": 0.05,
            "life": 22.7,
            "random": 0,
            "unCounterable": true
        },
        {
            "originPos": {
                "x": 10.0,
                "y": 19.0
            },
            "originVlc": {
                "x": 0,
                "y": 0
            },
            "speed": 3.0,
            "gravity": {
                "x": 0.0,
                "y": -1.5707963
            },
            "initialAngle": 0,
            "angleSpeed": 0.0,
            "useVelocityAngle": false,
            "polarForm": {
                "x": 1,
                "y": -1.5707963267948966
            },
            "radiusVlc": 0,
            "radiusAccel": 0,
            "thetaVlc": 0,
            "thetaAccel": 0,
            "polynomial": {
                "x": 0,
                "y": 0,
                "z": 0,
                "w": 0
            },
            "typeName": "tombstone",
            "scale": {
                "x": 1.6,
                "y": 1.6
            },
            "color": {
                "x": 0,
                "y": 0,
                "z": 0,
                "w": 0
            },
            "appearTime": 15.2,
            "appearDuration": 0.05,
            "life": 22.7,
            "random": 0,
            "unCounterable": true
        },
        {
            "originPos": {
                "x": 14.0,
                "y": 19.0
            },
            "originVlc": {
                "x": 0,
                "y": 0
            },
            "speed": 3.0,
            "gravity": {
                "x": 0.0,
                "y": -1.5707963
            },
            "initialAngle": 0,
            "angleSpeed": 0.0,
            "useVelocityAngle": false,
            "polarForm": {
                "x": 1,
                "y": -1.5707963267948966
            },
            "radiusVlc": 0,
            "radiusAccel": 0,
            "thetaVlc": 0,
            "thetaAccel": 0,
            "polynomial": {
                "x": 0,
                "y": 0,
                "z": 0,
                "w": 0
            },
            "typeName": "tombstone",
            "scale": {
                "x": 1.6,
                "y": 1.6
            },
            "color": {
                "x": 0,
                "y": 0,
                "z": 0,
                "w": 0
            },
            "appearTime": 15.2,
            "appearDuration": 0.05,
            "life": 22.7,
            "random": 0,
            "unCounterable": true
        },
        {
            "originPos": {
                "x": 26.0,
                "y": 19.0
            },
            "originVlc": {
                "x": 0,
                "y": 0
            },
            "speed": 3.0,
            "gravity": {
                "x": 0.0,
                "y": -1.5707963
            },
            "initialAngle": 0,
            "angleSpeed": 0.0,
            "useVelocityAngle": false,
            "polarForm": {
                "x": 1,
                "y": -1.5707963267948966
            },
            "radiusVlc": 0,
            "radiusAccel": 0,
            "thetaVlc": 0,
            "thetaAccel": 0,
            "polynomial": {
                "x": 0,
                "y": 0,
                "z": 0,
                "w": 0
            },
            "typeName": "tombstone",
            "scale": {
                "x": 1.6,
                "y": 1.6
            },
            "color": {
                "x": 0,
                "y": 0,
                "z": 0,
                "w": 0
            },
            "appearTime": 15.2,
            "appearDuration": 0.05,
            "life": 22.7,
            "random": 0,
            "unCounterable": true
        },
        {
            "originPos": {
                "x": 30.0,
                "y": 19.0
            },
            "originVlc": {
                "x": 0,
                "y": 0
            },
            "speed": 3.0,
            "gravity": {
                "x": 0.0,
                "y": -1.5707963
            },
            "initialAngle": 0,
            "angleSpeed": 0.0,
            "useVelocityAngle": false,
            "polarForm": {
                "x": 1,
                "y": -1.5707963267948966
            },
            "radiusVlc": 0,
            "radiusAccel": 0,
            "thetaVlc": 0,
            "thetaAccel": 0,
            "polynomial": {
                "x": 0,
                "y": 0,
                "z": 0,
                "w": 0
            },
            "typeName": "tombstone",
            "scale": {
                "x": 1.6,
                "y": 1.6
            },
            "color": {
                "x": 0,
                "y": 0,
                "z": 0,
                "w": 0
            },
            "appearTime": 15.2,
            "appearDuration": 0.05,
            "life": 22.7,
            "random": 0,
            "unCounterable": true
        }
    ],
    "homing": false,
    "isLaser": false
}